spmf/__init__.py
spmf/base.py
spmf/episode.py
spmf/seq_pat.py
spmf/binaries/__init__.py
spmf/binaries/spmf.jar
tests/__init__.py
tests/test_episode_mining.py
tests/test_seqpat_mining.py
tests/test_utils.py
spmf_wrapper-0.5.0.dist-info/LICENSE
spmf_wrapper-0.5.0.dist-info/METADATA
spmf_wrapper-0.5.0.dist-info/WHEEL
spmf_wrapper-0.5.0.dist-info/top_level.txt
spmf_wrapper-0.5.0.dist-info/RECORD
