Metadata-Version: 2.1
Name: spmf-wrapper
Version: 0.5.0
Summary: Python Wrapper for SPMF
Home-page: https://github.com/AakashVasudevan/Py-SPMF
Author: Aakash Vasudevan
Author-email: Aakash.Vasudevan@gmail.com
Keywords: SPMF,pattern,mining
Classifier: Programming Language :: Python :: 3
Classifier: License :: OSI Approved :: GNU General Public License v3 (GPLv3)
Classifier: Operating System :: OS Independent
Requires-Python: >=3.9
License-File: LICENSE
Requires-Dist: pandas >=1.4.3
Requires-Dist: install-jdk <=1.1.0
